bassextile_pkg/__init__.py
bassextilev2_pkg/__init__.py
bassextilev3_pkg/__init__.py
bassextilev3_pkg/base.py
bassextilev3_pkg/bisextile.py
bassextilev3_pkg-1.0.0.dist-info/LICENSE
bassextilev3_pkg-1.0.0.dist-info/METADATA
bassextilev3_pkg-1.0.0.dist-info/WHEEL
bassextilev3_pkg-1.0.0.dist-info/top_level.txt
bassextilev3_pkg-1.0.0.dist-info/RECORD
